nnoir_onnx/__init__.py
nnoir_onnx/_version.py
nnoir_onnx/freeze.py
nnoir_onnx/onnx.py
nnoir_onnx/onnx2nnoir.py
nnoir_onnx/operators/__init__.py
nnoir_onnx/operators/add.py
nnoir_onnx/operators/average_pool.py
nnoir_onnx/operators/batch_normalization.py
nnoir_onnx/operators/clip.py
nnoir_onnx/operators/concat.py
nnoir_onnx/operators/conv.py
nnoir_onnx/operators/cos.py
nnoir_onnx/operators/div.py
nnoir_onnx/operators/dropout.py
nnoir_onnx/operators/elu.py
nnoir_onnx/operators/erf.py
nnoir_onnx/operators/exp.py
nnoir_onnx/operators/flatten.py
nnoir_onnx/operators/gather.py
nnoir_onnx/operators/gemm.py
nnoir_onnx/operators/global_average_pool.py
nnoir_onnx/operators/hard_sigmoid.py
nnoir_onnx/operators/hard_swish.py
nnoir_onnx/operators/leaky_relu.py
nnoir_onnx/operators/lrn.py
nnoir_onnx/operators/lstm.py
nnoir_onnx/operators/mat_mul.py
nnoir_onnx/operators/max_pool.py
nnoir_onnx/operators/mul.py
nnoir_onnx/operators/pad.py
nnoir_onnx/operators/pow.py
nnoir_onnx/operators/prelu.py
nnoir_onnx/operators/reduce_mean.py
nnoir_onnx/operators/reduce_sum.py
nnoir_onnx/operators/relu.py
nnoir_onnx/operators/reshape.py
nnoir_onnx/operators/resize.py
nnoir_onnx/operators/sigmoid.py
nnoir_onnx/operators/sin.py
nnoir_onnx/operators/slice.py
nnoir_onnx/operators/softmax.py
nnoir_onnx/operators/split.py
nnoir_onnx/operators/sqrt.py
nnoir_onnx/operators/squeeze.py
nnoir_onnx/operators/sub.py
nnoir_onnx/operators/sum.py
nnoir_onnx/operators/tan.py
nnoir_onnx/operators/tanh.py
nnoir_onnx/operators/transpose.py
nnoir_onnx/operators/unsqueeze.py
nnoir_onnx/operators/utils.py
nnoir_onnx/operators/where.py
nnoir_onnx/py.typed
nnoir_onnx/utils.py
nnoir_onnx-1.6.0.dist-info/METADATA
nnoir_onnx-1.6.0.dist-info/WHEEL
nnoir_onnx-1.6.0.dist-info/entry_points.txt
nnoir_onnx-1.6.0.dist-info/RECORD
