Metadata-Version: 2.3
Name: nnoir-onnx
Version: 1.6.0
Summary: ONNX to NNOIR Converter
License: MIT
Keywords: nnoir,onnx,machine learning
Author: Idein Inc.
Requires-Python: >=3.9,<4.0
Classifier: Development Status :: 4 - Beta
Classifier: Intended Audience :: Developers
Classifier: License :: OSI Approved :: MIT License
Classifier: Programming Language :: Python :: 3
Classifier: Programming Language :: Python :: 3.9
Classifier: Programming Language :: Python :: 3.10
Classifier: Programming Language :: Python :: 3.11
Classifier: Programming Language :: Python :: 3.12
Classifier: Programming Language :: Python :: 3.13
Classifier: Programming Language :: Python :: 3 :: Only
Requires-Dist: importlib-metadata (>=4,<5)
Requires-Dist: msgpack (>=1,<2)
Requires-Dist: nnoir (>=1.4.0,<2.0.0)
Requires-Dist: numpy (>=1,<2)
Requires-Dist: onnx (<1.14.0)
Requires-Dist: onnxruntime (>=1.2.0,<2.0.0)
Requires-Dist: protobuf (>=3.8,<4.0)
Project-URL: Repository, https://github.com/Idein/nnoir/tree/master/nnoir-onnx
